{"GlobalPropertiesHash":"2ju5keCGrqK4Tdlqz4FAFAtAL+e9xwXdvP2191hVNdM=","FingerprintPatternsHash":"gq3WsqcKBUGTSNle7RKKyXRIwh7M8ccEqOqYvIzoM04=","PropertyOverridesHash":"8ZRc1sGeVrPBx4lD717BgRaQekyh78QKV9SKsdt638U=","InputHashes":["W0fBBIRYcNeEUU2loevzCL/6TTVy\u002Bi9vvM3hMbiWXXk=","j7S3bidSVidnKgyO\u002BKO8l/8IasXi0jYKTDkrIl7yGG0=","qJqQVLuu2tzLs2fkuWoH1LdpWUYvLBimRGhYkSxzLzY="],"CachedAssets":{"W0fBBIRYcNeEUU2loevzCL/6TTVy\u002Bi9vvM3hMbiWXXk=":{"Identity":"C:\\Users\\RTS\\source\\repos\\TRPGWorkspace\\TRPGWorkspace\\wwwroot\\index.html","SourceId":"TRPGWorkspace","SourceType":"Discovered","ContentRoot":"C:\\Users\\RTS\\source\\repos\\TRPGWorkspace\\TRPGWorkspace\\wwwroot\\","BasePath":"_content/TRPGWorkspace","RelativePath":"index#[.{fingerprint}]?.html","AssetKind":"All","AssetMode":"All","AssetRole":"Primary","AssetMergeBehavior":null,"AssetMergeSource":"","RelatedAsset":null,"AssetTraitName":null,"AssetTraitValue":null,"Fingerprint":"chqbswnkpb","Integrity":"0ObGR2IDSUJAUAhOXxH/1e08QkKJQLG\u002BwtBgl8YDpN4=","CopyToOutputDirectory":"Never","CopyToPublishDirectory":"PreserveNewest","OriginalItemSpec":"wwwroot\\index.html","FileLength":12443,"LastWriteTime":"2025-12-19T17:04:10.4255428+00:00"}},"CachedCopyCandidates":{}}